extra_demucs/__init__.py
extra_demucs/downloader.py
extra_demucs/ffmpeg_utils.py
extra_demucs/separate.py
extra_demucs-0.7.0.dist-info/LICENSE
extra_demucs-0.7.0.dist-info/METADATA
extra_demucs-0.7.0.dist-info/WHEEL
extra_demucs-0.7.0.dist-info/RECORD
