Metadata-Version: 2.3
Name: extra-demucs
Version: 0.7.0
Summary: Extended Demucs with yt-dlp and Video support.
License: MIT
Keywords: demucs,audio-separation,vocal-extract,music-source-separation,yt-dlp,ffmpeg,deep-learning,torch-audio,music-remove
Author: mohammadmansour200
Author-email: mohammadamansour03@gmail.com
Requires-Python: >=3.9
Classifier: License :: OSI Approved :: MIT License
Classifier: Programming Language :: Python :: 3
Classifier: Programming Language :: Python :: 3.9
Classifier: Programming Language :: Python :: 3.10
Classifier: Programming Language :: Python :: 3.11
Classifier: Programming Language :: Python :: 3.12
Classifier: Programming Language :: Python :: 3.13
Requires-Dist: demucs (>=4.0.1,<5.0.0)
Requires-Dist: torchaudio (==2.7.1)
Requires-Dist: validators (>=0.35.0,<0.36.0)
Requires-Dist: yt-dlp (>=2025.8.22)
